LICENSE
MANIFEST.in
README.md
setup.py
stackauth.py
demo/experience.py
demo/highest_voted.py
demo/narcissism.py
demo/object_explorer.py
demo/question.py
demo/recent_questions.py
demo/search.py
demo/stats.py
demo/versus.py
py_stackexchange.egg-info/PKG-INFO
py_stackexchange.egg-info/SOURCES.txt
py_stackexchange.egg-info/dependency_links.txt
py_stackexchange.egg-info/requires.txt
py_stackexchange.egg-info/top_level.txt
stackexchange/__init__.py
stackexchange/core.py
stackexchange/models.py
stackexchange/site.py
stackexchange/sites.py
stackexchange/web.py